harness/GameControllerDB.py
harness/__init__.py
pysdl2_harness-0.2.dist-info/WHEEL
pysdl2_harness-0.2.dist-info/RECORD
pysdl2_harness-0.2.dist-info/METADATA
pysdl2_harness-0.2.dist-info/DESCRIPTION.rst
pysdl2_harness-0.2.dist-info/top_level.txt
pysdl2_harness-0.2.dist-info/metadata.json
