Metadata-Version: 2.0
Name: pysdl2-harness
Version: 0.2
Summary: Some simple classes to make working with pysdl2 easier
Home-page: https://github.com/reidrac/pysdl2-harness
Author: Juan J. Martinez
Author-email: jjm@usebox.net
License: MIT
Keywords: pysdl2 game sdl
Platform: UNKNOWN
Classifier: Development Status :: 4 - Beta
Classifier: Operating System :: OS Independent
Classifier: Intended Audience :: Developers
Classifier: Programming Language :: Python :: 3
Classifier: Topic :: Games/Entertainment
Classifier: Topic :: Software Development :: Libraries :: Python Modules
Classifier: License :: OSI Approved :: MIT License
Requires-Dist: pysdl2
